feature_change/__init__.py
feature_change/change.py
feature_change-0.1.0.dist-info/WHEEL
feature_change-0.1.0.dist-info/METADATA
feature_change-0.1.0.dist-info/RECORD
